tombstones/__init__.py
tombstones/admin.py
tombstones/apps.py
tombstones/models.py
tombstones/migrations/0001_initial.py
tombstones/migrations/__init__.py
django_tombstones-0.1.17.dist-info/LICENSE
django_tombstones-0.1.17.dist-info/METADATA
django_tombstones-0.1.17.dist-info/WHEEL
django_tombstones-0.1.17.dist-info/top_level.txt
django_tombstones-0.1.17.dist-info/RECORD
